[{"type": "Feature", "geometry": {"type": "Point", "coordinates": [0.214405, 51.3693364]}, "properties": {"title": "Castle Hotel, Dartford"}}, {"type": "Feature", "geometry": {"type": "Point", "coordinates": [-2.3844996, 53.77923910000001]}, "properties": {"title": "Castle Hotel, Accrington Town, Accrington"}}, {"type": "Feature", "geometry": {"type": "Point", "coordinates": [-0.6071658000000001, 51.4818792]}, "properties": {"title": "Castle Hotel, Windsor Central, Windsor"}}, {"type": "Feature", "geometry": {"type": "Point", "coordinates": [-1.2283458999999999, 52.6375152]}, "properties": {"title": "Castle Hotel, Leicester"}}, {"type": "Feature", "geometry": {"type": "Point", "coordinates": [-2.233807, 53.48369200000001]}, "properties": {"title": "Castle Hotel, Manchester"}}, {"type": "Feature", "geometry": {"type": "Point", "coordinates": [0.2703292, 52.4029078]}, "properties": {"title": "The Castle Hotel, Ely City, Ely"}}, {"type": "Feature", "geometry": {"type": "Point", "coordinates": [0.3786958, 52.6038399]}, "properties": {"title": "Castle Hotel, Downham Market Town, Downham Market"}}, {"type": "Feature", "geometry": {"type": "Point", "coordinates": [-1.7163039, 55.606887300000004]}, "properties": {"title": "Castle Hotel, Bamburgh Village, Bamburgh"}}, {"type": "Feature", "geometry": {"type": "Point", "coordinates": [-2.9979892999999995, 52.4949412]}, "properties": {"title": "Castle Hotel, Bishops Castle Central, Bishops Castle"}}, {"type": "Feature", "geometry": {"type": "Point", "coordinates": [-0.311837, 50.882845]}, "properties": {"title": "Castle Hotel, Bramber, Steyning"}}, {"type": "Feature", "geometry": {"type": "Point", "coordinates": [-4.2591817, 52.242425]}, "properties": {"title": "Castle Hotel, Aberaeron Town, Aberaeron"}}, {"type": "Feature", "geometry": {"type": "Point", "coordinates": [-4.3015988, 51.8588033]}, "properties": {"title": "Castle Hotel, Carmarthen Town, Carmarthen"}}, {"type": "Feature", "geometry": {"type": "Point", "coordinates": [-4.9686512, 51.8020561]}, "properties": {"title": "The Castle Hotel, Haverfordwest Town, Haverfordwest"}}, {"type": "Feature", "geometry": {"type": "Point", "coordinates": [-3.7971502, 51.9936253]}, "properties": {"title": "The Castle Hotel, Llandovery Town, Llandovery"}}, {"type": "Feature", "geometry": {"type": "Point", "coordinates": [-3.0850793999999997, 51.772335999999996]}, "properties": {"title": "Castle Hotel, Blaenavon Central, Blaenavon"}}, {"type": "Feature", "geometry": {"type": "Point", "coordinates": [-3.8290664, 53.2813345]}, "properties": {"title": "Castle Hotel, Conwy Central, Conwy"}}, {"type": "Feature", "geometry": {"type": "Point", "coordinates": [-3.2595829, 51.4060925]}, "properties": {"title": "Castle Hotel, Barry Docks, Barry"}}, {"type": "Feature", "geometry": {"type": "Point", "coordinates": [-3.8052716, 51.6636204]}, "properties": {"title": "The Castle Hotel, Neath Central, Neath"}}, {"type": "Feature", "geometry": {"type": "Point", "coordinates": [-3.8524447, 51.7208239]}, "properties": {"title": "Castle Hotel, Swansea"}}, {"type": "Feature", "geometry": {"type": "Point", "coordinates": [-2.5166915000000003, 56.00358539999999]}, "properties": {"title": "Castle Hotel, Dunbar Central, Dunbar"}}, {"type": "Feature", "geometry": {"type": "Point", "coordinates": [-2.72361, 52.8558556]}, "properties": {"title": "The Castle Hotel, Shrewsbury"}}, {"type": "Feature", "geometry": {"type": "Point", "coordinates": [-2.3178103, 54.5263919]}, "properties": {"title": "Castle Hotel, Kirkby Stephen"}}, {"type": "Feature", "geometry": {"type": "Point", "coordinates": [1.0769318, 51.0802635]}, "properties": {"title": "Castle Hotel, Hythe"}}, {"type": "Feature", "geometry": {"type": "Point", "coordinates": [-3.3103745000000004, 53.1146104]}, "properties": {"title": "The Castle Hotel (JD Wetherspoon), Ruthin Central, Ruthin"}}, {"type": "Feature", "geometry": {"type": "Point", "coordinates": [-2.2554537, 55.6502546]}, "properties": {"title": "Castle Hotel, Coldstream Town, Coldstream"}}, {"type": "Feature", "geometry": {"type": "Point", "coordinates": [-3.2338461, 51.99783979999999]}, "properties": {"title": "The Castle Hotel, Brecon"}}, {"type": "Feature", "geometry": {"type": "Point", "coordinates": [-4.0796529, 52.1128625]}, "properties": {"title": "Castle Hotel, Lampeter Town, Lampeter"}}, {"type": "Feature", "geometry": {"type": "Point", "coordinates": [-3.8826627, 51.9382575]}, "properties": {"title": "Castle Hotel, Llangadog Town, Llangadog"}}, {"type": "Feature", "geometry": {"type": "Point", "coordinates": [-3.2465303, 51.7722468]}, "properties": {"title": "Castle Hotel, Tredegar Town, Tredegar"}}]